<?xml version="1.0" encoding="UTF-8"?>
<beans xmlns="http://www.springframework.org/schema/beans"
       xmlns:xsi="http://www.w3.org/2001/XMLSchema-instance"
       xsi:schemaLocation="http://www.springframework.org/schema/beans http://www.springframework.org/schema/beans/spring-beans.xsd">

    <bean id="taskJobDetail" class="org.springframework.scheduling.quartz.MethodInvokingJobDetailFactoryBean">
        <property name="targetObject" ref="job.taskTarget"/>
        <property name="targetMethod" value="execute"/>
        <property name="concurrent" value="false"/>
    </bean>
    <bean id="taskTrigger" class="org.springframework.scheduling.quartz.CronTriggerBean">
        <property name="jobDetail" ref="taskJobDetail"/>
        <property name="cronExpression" value="* 0/${server.space} * * * ?"/>
    </bean>

    <bean class="org.springframework.scheduling.quartz.SchedulerFactoryBean">
        <property name="triggers">
            <list>
                <ref bean="taskTrigger"/>
            </list>
        </property>
    </bean>

    <bean id="taskExecutor" class="org.springframework.scheduling.concurrent.ThreadPoolTaskExecutor">
        <property name="corePoolSize" value="5"/>
        <property name="maxPoolSize" value="100"/>
        <property name="queueCapacity" value="25"/>
    </bean>
</beans>